flake8_staged_diff/__init__.py
flake8_staged_diff/main.py
flake8_staged_diff-0.3.0.dist-info/LICENSE
flake8_staged_diff-0.3.0.dist-info/METADATA
flake8_staged_diff-0.3.0.dist-info/WHEEL
flake8_staged_diff-0.3.0.dist-info/entry_points.txt
flake8_staged_diff-0.3.0.dist-info/top_level.txt
flake8_staged_diff-0.3.0.dist-info/RECORD
