Metadata-Version: 2.1
Name: flake8-staged-diff
Version: 0.3.0
Summary: flake8 wrapper to run only on modified/staged code
Home-page: https://github.com/bagerard/flake8-staged-diff
Maintainer: Bastien Gerard
Maintainer-email: bast.gerard@gmail.com
License: MIT License
Keywords: flake8 diff linter pre-commit
Classifier: Programming Language :: Python :: 3
Classifier: Topic :: Software Development :: Quality Assurance
License-File: LICENSE
Requires-Dist: flake8
